README.md
setup.py
batch_async_http/__init__.py
batch_async_http/main.py
batch_async_http.egg-info/PKG-INFO
batch_async_http.egg-info/SOURCES.txt
batch_async_http.egg-info/dependency_links.txt
batch_async_http.egg-info/requires.txt
batch_async_http.egg-info/top_level.txt