Metadata-Version: 2.1
Name: batch-async-http
Version: 0.0.1
Summary: Decorator for async batch calling via http requests
Home-page: https://https://github.com/MiesnerJacob/batch_async_http
Author: Jacob Miesner
Author-email: miesner.jacob@gmail.com
License: GPLv3
Keywords: async,batch,http,requests
Platform: UNKNOWN
Classifier: Development Status :: 4 - Beta
Classifier: Programming Language :: Python
Classifier: Intended Audience :: Developers
Classifier: License :: OSI Approved :: GNU General Public License v3 (GPLv3)
Classifier: Natural Language :: English
Classifier: Topic :: Internet :: WWW/HTTP :: HTTP Servers
Classifier: Topic :: Scientific/Engineering :: Artificial Intelligence
Requires-Python: >=3.6
